snakemake_scheduler_plugin_firstfit/__init__.py
snakemake_scheduler_plugin_firstfit-0.1.2.dist-info/METADATA
snakemake_scheduler_plugin_firstfit-0.1.2.dist-info/WHEEL
snakemake_scheduler_plugin_firstfit-0.1.2.dist-info/licenses/LICENSE
snakemake_scheduler_plugin_firstfit-0.1.2.dist-info/RECORD
